opgg/__init__.py
opgg/cacher.py
opgg/champion.py
opgg/exceptions.py
opgg/game.py
opgg/keyword.py
opgg/opgg.py
opgg/opscore.py
opgg/params.py
opgg/response.py
opgg/search_result.py
opgg/season.py
opgg/summoner.py
opgg/utils.py
opgg_py-3.1.0.dist-info/licenses/LICENSE
opgg_py-3.1.0.dist-info/METADATA
opgg_py-3.1.0.dist-info/WHEEL
opgg_py-3.1.0.dist-info/top_level.txt
opgg_py-3.1.0.dist-info/RECORD
