Metadata-Version: 2.4
Name: opgg.py
Version: 3.1.0
Summary: An unofficial Python library for scraping/accessing data from OP.GG
Author: ShoobyDoo
License-Expression: GPL-3.0-or-later
Project-URL: Homepage, https://github.com/ShoobyDoo/OPGG.py
Project-URL: Bug Reports, https://github.com/ShoobyDoo/OPGG.py/issues
Project-URL: Source, https://github.com/ShoobyDoo/OPGG.py
Keywords: opgg,league-of-legends,web-scraping,summoner,data,riot-api
Classifier: Development Status :: 3 - Alpha
Classifier: Intended Audience :: Developers
Classifier: Topic :: Software Development
Classifier: Programming Language :: Python :: 3
Classifier: Programming Language :: Python :: 3.12
Classifier: Programming Language :: Python :: 3.13
Classifier: Programming Language :: Python :: 3 :: Only
Requires-Python: >=3.12
License-File: LICENSE
Requires-Dist: aiohttp>=3.13.0
Requires-Dist: pydantic>=2.12.0
Requires-Dist: fake-useragent>=2.2.0
Provides-Extra: dev
Requires-Dist: ruff>=0.14.0; extra == "dev"
Requires-Dist: pytest>=8.0.0; extra == "dev"
Requires-Dist: pytest-asyncio>=0.23.0; extra == "dev"
Requires-Dist: pytest-cov>=4.1.0; extra == "dev"
Requires-Dist: pytest-mock>=3.12.0; extra == "dev"
Requires-Dist: aioresponses>=0.7.6; extra == "dev"
Requires-Dist: mypy>=1.8.0; extra == "dev"
Dynamic: license-file
